docs/algorithm_descriptions.pdf
docs/cuthbert_bbc_comparison.html
docs/dilms_example.html
docs/user-guide.txt
iceberg/__init__.py
iceberg/conftest.py
iceberg/estimate.py
iceberg/simulate.py
iceberg/tests/test_iceberg.py
iceberg_est-1.0.0.dist-info/LICENSE
iceberg_est-1.0.0.dist-info/METADATA
iceberg_est-1.0.0.dist-info/WHEEL
iceberg_est-1.0.0.dist-info/top_level.txt
iceberg_est-1.0.0.dist-info/RECORD
