Metadata-Version: 2.1
Name: iceberg-est
Version: 1.0.0
Summary: Musicologically motivated population size estimation
Home-page: https://github.com/wcwatson/iceberg
Author: William Watson
Author-email: wcwatson92@gmail.com
License: MIT
Platform: UNKNOWN
Classifier: Development Status :: 4 - Beta
Classifier: Intended Audience :: Science/Research
Classifier: Topic :: Scientific/Engineering :: Mathematics
Classifier: License :: OSI Approved :: MIT License
Classifier: Programming Language :: Python :: 3
Classifier: Programming Language :: Python :: 3.8
Requires-Python: >=3.6, <4
Requires-Dist: numpy
